{
 "cells": [
  {
   "cell_type": "code",
   "execution_count": 2,
   "metadata": {},
   "outputs": [
    {
     "name": "stdout",
     "output_type": "stream",
     "text": [
      "  3           0 LOAD_CONST               1 (10)\n",
      "              2 STORE_FAST               0 (a)\n",
      "\n",
      "  4           4 LOAD_CONST               2 (20)\n",
      "              6 STORE_FAST               1 (b)\n",
      "\n",
      "  5           8 LOAD_GLOBAL              0 (print)\n",
      "             10 LOAD_FAST                0 (a)\n",
      "             12 LOAD_FAST                1 (b)\n",
      "             14 BINARY_ADD\n",
      "             16 CALL_FUNCTION            1\n",
      "             18 POP_TOP\n",
      "             20 LOAD_CONST               0 (None)\n",
      "             22 RETURN_VALUE\n"
     ]
    }
   ],
   "source": [
    "import dis\n",
    "def sum():\n",
    "    a=10\n",
    "    b=20\n",
    "    print(a+b)\n",
    "dis.dis(sum)"
   ]
  },
  {
   "cell_type": "code",
   "execution_count": null,
   "metadata": {},
   "outputs": [],
   "source": []
  }
 ],
 "metadata": {
  "kernelspec": {
   "display_name": "Python 3",
   "language": "python",
   "name": "python3"
  },
  "language_info": {
   "codemirror_mode": {
    "name": "ipython",
    "version": 3
   },
   "file_extension": ".py",
   "mimetype": "text/x-python",
   "name": "python",
   "nbconvert_exporter": "python",
   "pygments_lexer": "ipython3",
   "version": "3.6.5"
  }
 },
 "nbformat": 4,
 "nbformat_minor": 2
}
